e2xcore/__init__.py
e2xcore/__version__.py
e2xcore/api/__init__.py
e2xcore/api/api.py
e2xcore/app/__init__.py
e2xcore/app/app.py
e2xcore/handlers/__init__.py
e2xcore/handlers/base.py
e2xcore/utils/__init__.py
e2xcore/utils/e2xgrader_cells.py
e2xcore/utils/nbgrader_cells.py
e2xcore/utils/utils.py
e2xcore-0.0.5.dist-info/METADATA
e2xcore-0.0.5.dist-info/WHEEL
e2xcore-0.0.5.dist-info/licenses/LICENSE
e2xcore-0.0.5.dist-info/RECORD
